afinderx/__init__.py
afinderx/afinderx.py
afinderx-1.0.dist-info/METADATA
afinderx-1.0.dist-info/WHEEL
afinderx-1.0.dist-info/entry_points.txt
afinderx-1.0.dist-info/top_level.txt
afinderx-1.0.dist-info/RECORD
