Metadata-Version: 2.4
Name: afinderx
Version: 1.0
Summary: Android opened devices finder and port scanner
Author: Babar Ali Jamali
Author-email: babar995@gmail.com
Requires-Python: >=3.6
Dynamic: author
Dynamic: author-email
Dynamic: requires-python
Dynamic: summary
